Metadata-Version: 1.1
Name: django-note
Version: 1.1.1
Summary: A simple Django app to conduct Web-based note lists.
Home-page: https://www.example.com/
Author: Skochinskyi Dmytro
Author-email: skodmy@gmail.com
License: GPL-3.0
Platform: UNKNOWN
Classifier: Environment :: Web Environment
Classifier: Framework :: Django
Classifier: Framework :: Django :: 1.11
Classifier: Intended Audience :: Developers
Classifier: License :: OSI Approved :: GNU General Public License v3 (GPLv3)
Classifier: Operating System :: OS Independent
Classifier: Programming Language :: Python :: 3.6
Classifier: Topic :: Internet :: WWW/HTTP
Classifier: Topic :: Internet :: WWW/HTTP :: Dynamic Content
